SPI/rtl/slave.v
module slave(
	input wire clk,
	input wire rst_n,
	input wire mosi,
	input wire sck,
	input wire cs,
	output reg miso,
	output reg [7:0] data_out
);

reg [7:0] shift_reg;
reg [2:0] bit_cnt;

always @(posedge clk or negedge rst_n) begin
	if(!rst_n) begin
		miso <= 1'b0;
		data_out <= 8'h00;
		shift_reg <= 8'h00;
		bit_cnt <= 3'b000;
	end else if (cs == 1) begin
		if(sck) begin
			shift_reg <= {shift_reg[6:0], mosi};
			if(bit_cnt == 3'b111) begin
				data_out <= {shift_reg[6:0], mosi};
			end
			bit_cnt <= bit_cnt + 1'b1;
		end
		miso <= shift_reg[7];
	end else begin
		miso <= 1'b0;
	end
end

endmodule

SPI/rtl/master.v
module master(
	input wire clk,
	input wire rst_n,
	input wire start,
	input wire miso,
	input wire [7:0] data_in,
	output reg mosi,
	output reg sck,
	output reg cs,
	output reg done
);

localparam IDLE = 2'b00;
localparam START = 2'b01;
localparam TRANSFER = 2'b10;
localparam DONE = 2'b11;

reg [1:0] state, next_state;
reg [3:0] bit_cnt; // counting bits transmited.
reg [7:0] shift_reg; // Register for the bit translation.
reg shift_sck; // Used to create the signal SCK

// Defining the next state.
always @(posedge clk or negedge rst_n) begin
	if (!rst_n) begin
		state <= IDLE;
	end else begin
		state <= next_state;
	end
end

// FSM logic to control the SPI signals
always @(*) begin
	case(state)
		IDLE: begin
			if(start) begin
				next_state <= START; // transfer to the START state when the start signal is 1
			end else begin
				next_state <= IDLE;
			end
		end
		START: next_state <= TRANSFER; // after setuping before transfer to the TRANSFER state
		TRANSFER: begin
			if(bit_cnt == 4'b1000 && shift_sck) begin
				next_state <= DONE; // When the 8 bits are transmited , transfer to the DONE state
			end else begin
				next_state <= TRANSFER; // continue to transmit datas.
			end
		end
		DONE: next_state <= IDLE; // after communication, return to the IDLE state.
		default: next_state <= IDLE;
	endcase
end

// Logic to create the SPI signal
always @(posedge clk or negedge rst_n) begin
	if(!rst_n) begin
		mosi <= 1'b0;
		sck <= 1'b0;
		cs <= 1'b0;
		//data_out <= 8'h00;
		done <= 1'b0;
		bit_cnt <= 4'b0;
		shift_reg <= 8'h00;
		shift_sck <= 1'b0;
	end else begin
		case(state)
			IDLE: begin
				cs <= 1'b0; // cancel activate cs when the state is IDLE.
				done <= 1'b0;
				mosi <= 0;
				sck <= 1'b0;
				shift_sck <= 1'b0;
				//data_out <= 8'h00;
			end
			START: begin
				cs <= 1'b1;
				shift_reg <= data_in; // setup data need to send
				bit_cnt <= 4'b000;
				done <= 1'b0;
			end
			TRANSFER: begin
				shift_sck = ~shift_sck; // generate SCK clock pulse
				sck <= shift_sck;
				if(shift_sck) begin
					mosi <= shift_reg[7];
					shift_reg <= {shift_reg[6:0],1'b0};
					bit_cnt <= bit_cnt + 1'b1;
				end
			end
			DONE: begin
				cs <= 1'b0;
				done <= 1'b1;
			end
			default: begin
				cs <= 1'b0;
				done <= 1'b0;
			end
		endcase
	end
end
endmodule

SPI/rtl/top.v
module spi (
    input wire clk,
    input wire rst_n,
    input wire start,
    input wire [7:0] data_in,
    input wire sel, // Select signal to choose between slave 1 and slave 2
    output reg [7:0] data_out1,
    output reg [7:0] data_out2,
    output reg done
);

    // Internal signals
    wire mosi;
    wire sck;
    wire cs;
    wire miso1, miso2;
    reg miso;

    wire [7:0] master_data_out;
    wire master_done;
    wire [7:0] slave_data_out1;
    wire [7:0] slave_data_out2;

    // Instantiate the master module
    master ic1(
        .clk(clk), 
        .rst_n(rst_n), 
        .start(start), 
        .miso(miso), 
        .data_in(data_in), 
        .mosi(mosi), 
        .sck(sck), 
        .cs(cs), 
        .done(master_done)
    );

    // Instantiate slave 1
    slave ic2(
        .clk(clk), 
        .rst_n(rst_n), 
        .mosi(mosi), 
        .sck(sck), 
        .cs(cs & ~sel), // Activate slave 1 when sel = 0
        .miso(miso1), 
        .data_out(slave_data_out1)
    );

    // Instantiate slave 2
    slave ic3(
        .clk(clk), 
        .rst_n(rst_n), 
        .mosi(mosi), 
        .sck(sck), 
        .cs(cs & sel), // Activate slave 2 when sel = 1
        .miso(miso2), 
        .data_out(slave_data_out2)
    );

    // Output logic for `miso`
    always @(*) begin
        // Select the appropriate slave's miso line based on `sel`
        //miso = sel ? miso2 : miso1; 
	if (!sel) begin
		miso <= miso1;
	end else begin
		miso <= miso2;
	end
    end
  
    // Handle data outputs and completion signal
    always @(posedge clk or negedge rst_n) begin
        if (!rst_n) begin
            data_out1 <= 8'h00;
            data_out2 <= 8'h00;
            done <= 1'b0;
        end else if (!sel) begin
            data_out1 <= slave_data_out1; // Output from slave 1
	    data_out2 <= 8'h00;
	    done <= master_done;
    	end else begin
	    data_out1 <= 8'h00;
            data_out2 <= slave_data_out2; // Output from slave 2
            done <= master_done;         // Done signal from master
        end
    end
endmodule

SPI/tb/test_bench.v
`timescale 1ns/1ps
module test_bench;
	reg clk;
	reg rst_n;
	reg start;
	reg [7:0] data_in;
	reg sel;
	wire [7:0] data_out1;
	wire [7:0] data_out2;
	wire done;

	reg [7:0] expected;
	integer i;

	spi dut(
		.clk(clk),
		.rst_n(rst_n),
		.start(start),
		.data_in(data_in),
		.sel(sel),
		.data_out1(data_out1),
		.data_out2(data_out2),
		.done(done)
	);

	initial clk = 0;
		always #5 clk = ~clk;

	task verify;
		input [7:0] test_data;
		input sel;
		reg [7:0] exp_data;
		begin
			data_in = 8'h00;
			start = 1'b0;
			@(posedge clk);
			data_in = test_data;
			start = 1'b1;
			@(posedge clk);
			start = 1'b0;
			wait(done);

			exp_data = test_data;
			@(posedge clk);
			$display("At time: %t, rst_n = 1'b%b, start = 1'b%b, data_in = 8'b%b, sel = 1'b%b", $time, rst_n, start, data_in, sel);
			if((sel == 0 && data_out1 == exp_data && data_out2 == 8'h00) || (sel == 1 && data_out2 == exp_data && data_out1 == 8'h00)) begin
				$display("-----------------------------------------------------------------------------------------------------------------");
				$display("PASSED: Sel = 1'b%b, Sent = 0x%h, Received: 0x%h", sel, test_data, sel ? data_out2 : data_out1);
				$display("-----------------------------------------------------------------------------------------------------------------");
			end else begin
				$display("-----------------------------------------------------------------------------------------------------------------");
				$display("FAILED: Sel = 1'b%b, Sent = 0x%h, Received: 0x%h", sel, test_data, sel ? data_out2 : data_out1);
				$display("-----------------------------------------------------------------------------------------------------------------");
			end
		end
	endtask

	initial begin
		$dumpfile("test_bench.vcd");
		$dumpvars(0, test_bench);

		$display("-----------------------------------------------------------------------------------------------------------------------------");
		$display("--------------------------------------------TESTBENCH FOR SPI COMMUNICATION--------------------------------------------------");
		$display("-----------------------------------------------------------------------------------------------------------------------------");

		rst_n = 0;
		@(posedge clk);
		rst_n = 1;
		sel = 1'b1;
		@(posedge clk);
		verify(8'hf0,1);

		sel = 1'b0;
		@(posedge clk);
		verify(8'h55,sel);

		sel = 1'b0;
		@(posedge clk);
		verify(8'hff,sel);
		
		for (i = 0; i < 20; i = i + 1) begin
			sel = $random % 2;
			@(posedge clk);
			expected = $random % 256;
			verify(expected, sel);
		end

		$display("--------------------------------- COMPLETED TESTBENCH -----------------------------------------------------------------------");

		#100;
		$finish;

	end
endmodule

SPI/sim/test_bench.vcd
$date
	Tue Jan 14 17:16:27 2025
$end
$version
	Icarus Verilog
$end
$timescale
	1ps
$end
$scope module test_bench $end
$var wire 1 ! done $end
$var wire 8 " data_out2 [7:0] $end
$var wire 8 # data_out1 [7:0] $end
$var reg 1 $ clk $end
$var reg 8 % data_in [7:0] $end
$var reg 8 & expected [7:0] $end
$var reg 1 ' rst_n $end
$var reg 1 ( sel $end
$var reg 1 ) start $end
$var integer 32 * i [31:0] $end
$scope module dut $end
$var wire 1 $ clk $end
$var wire 8 + data_in [7:0] $end
$var wire 1 ' rst_n $end
$var wire 1 ( sel $end
$var wire 1 ) start $end
$var wire 8 , slave_data_out2 [7:0] $end
$var wire 8 - slave_data_out1 [7:0] $end
$var wire 1 . sck $end
$var wire 1 / mosi $end
$var wire 1 0 miso2 $end
$var wire 1 1 miso1 $end
$var wire 1 2 master_done $end
$var wire 1 3 cs $end
$var reg 8 4 data_out1 [7:0] $end
$var reg 8 5 data_out2 [7:0] $end
$var reg 1 ! done $end
$var reg 1 6 miso $end
$scope module ic1 $end
$var wire 1 $ clk $end
$var wire 8 7 data_in [7:0] $end
$var wire 1 6 miso $end
$var wire 1 ' rst_n $end
$var wire 1 ) start $end
$var parameter 2 8 DONE $end
$var parameter 2 9 IDLE $end
$var parameter 2 : START $end
$var parameter 2 ; TRANSFER $end
$var reg 4 < bit_cnt [3:0] $end
$var reg 1 3 cs $end
$var reg 1 2 done $end
$var reg 1 / mosi $end
$var reg 2 = next_state [1:0] $end
$var reg 1 . sck $end
$var reg 8 > shift_reg [7:0] $end
$var reg 1 ? shift_sck $end
$var reg 2 @ state [1:0] $end
$upscope $end
$scope module ic2 $end
$var wire 1 $ clk $end
$var wire 1 A cs $end
$var wire 1 / mosi $end
$var wire 1 ' rst_n $end
$var wire 1 . sck $end
$var reg 3 B bit_cnt [2:0] $end
$var reg 8 C data_out [7:0] $end
$var reg 1 1 miso $end
$var reg 8 D shift_reg [7:0] $end
$upscope $end
$scope module ic3 $end
$var wire 1 $ clk $end
$var wire 1 E cs $end
$var wire 1 / mosi $end
$var wire 1 ' rst_n $end
$var wire 1 . sck $end
$var reg 3 F bit_cnt [2:0] $end
$var reg 8 G data_out [7:0] $end
$var reg 1 0 miso $end
$var reg 8 H shift_reg [7:0] $end
$upscope $end
$upscope $end
$scope task verify $end
$var reg 8 I exp_data [7:0] $end
$var reg 1 J sel $end
$var reg 8 K test_data [7:0] $end
$upscope $end
$upscope $end
$enddefinitions $end
$comment Show the parameter values. $end
$dumpall
b10 ;
b1 :
b0 9
b11 8
$end
#0
$dumpvars
bx K
xJ
bx I
b0 H
b0 G
b0 F
0E
b0 D
b0 C
b0 B
0A
b0 @
0?
b0 >
b0 =
b0 <
bx 7
06
b0 5
b0 4
03
02
01
00
0/
0.
b0 -
b0 ,
bx +
bx *
x)
x(
0'
bx &
bx %
0$
b0 #
b0 "
0!
$end
#5000
1(
1'
1$
#10000
0$
#15000
0)
b0 %
b0 +
b0 7
1J
b11110000 K
1$
#20000
0$
#25000
b1 =
1)
b11110000 %
b11110000 +
b11110000 7
1$
#30000
0$
#35000
b10 =
b1 @
0)
1$
#40000
0$
#45000
1E
b11110000 >
13
b10 @
1$
#50000
0$
#55000
b1 <
b11100000 >
1/
1.
1?
1$
#60000
0$
#65000
b1 F
b1 H
0.
0?
1$
#70000
0$
#75000
b10 <
b11000000 >
1.
1?
1$
#80000
0$
#85000
b10 F
b11 H
0.
0?
1$
#90000
0$
#95000
b11 <
b10000000 >
1.
1?
1$
#100000
0$
#105000
b11 F
b111 H
0.
0?
1$
#110000
0$
#115000
b100 <
b0 >
1.
1?
1$
#120000
0$
#125000
b100 F
b1111 H
0.
0?
1$
#130000
0$
#135000
b101 <
0/
1.
1?
1$
#140000
0$
#145000
b101 F
b11110 H
0.
0?
1$
#150000
0$
#155000
b110 <
1.
1?
1$
#160000
0$
#165000
b110 F
b111100 H
0.
0?
1$
#170000
0$
#175000
b111 <
1.
1?
1$
#180000
0$
#185000
b111 F
b1111000 H
0.
0?
1$
#190000
0$
#195000
b11 =
b1000 <
1.
1?
1$
#200000
0$
#205000
b0 =
b0 F
b11110000 ,
b11110000 G
b11110000 H
0.
b11 @
0?
1$
#210000
0$
#215000
16
0E
b0 @
12
03
10
b11110000 "
b11110000 5
1$
#220000
0$
#225000
06
b11110000 I
1!
00
02
1$
#230000
0$
#235000
0!
b0 "
b0 5
0(
1$
#240000
0$
#245000
b0 %
b0 +
b0 7
0J
b1010101 K
1$
#250000
0$
#255000
b1 =
1)
b1010101 %
b1010101 +
b1010101 7
1$
#260000
0$
#265000
b10 =
b1 @
0)
1$
#270000
0$
#275000
1A
b10 @
b0 <
b1010101 >
13
1$
#280000
0$
#285000
b1 <
b10101010 >
1.
1?
1$
#290000
0$
#295000
0.
b1 B
0?
1$
#300000
0$
#305000
b10 <
b1010100 >
1/
1.
1?
1$
#310000
0$
#315000
0.
b10 B
b1 D
0?
1$
#320000
0$
#325000
b11 <
b10101000 >
0/
1.
1?
1$
#330000
0$
#335000
0.
b11 B
b10 D
0?
1$
#340000
0$
#345000
b100 <
b1010000 >
1/
1.
1?
1$
#350000
0$
#355000
0.
b100 B
b101 D
0?
1$
#360000
0$
#365000
b101 <
b10100000 >
0/
1.
1?
1$
#370000
0$
#375000
0.
b101 B
b1010 D
0?
1$
#380000
0$
#385000
b110 <
b1000000 >
1/
1.
1?
1$
#390000
0$
#395000
0.
b110 B
b10101 D
0?
1$
#400000
0$
#405000
b111 <
b10000000 >
0/
1.
1?
1$
#410000
0$
#415000
0.
b111 B
b101010 D
0?
1$
#420000
0$
#425000
b11 =
b1000 <
b0 >
1/
1.
1?
1$
#430000
0$
#435000
b0 =
b11 @
0.
b0 B
b1010101 -
b1010101 C
b1010101 D
0?
1$
#440000
0$
#445000
0A
b1010101 #
b1010101 4
12
03
b0 @
1$
#450000
0$
#455000
b1010101 I
0/
02
1!
1$
#460000
0$
#465000
0!
1$
#470000
0$
#475000
b0 %
b0 +
b0 7
b11111111 K
1$
#480000
0$
#485000
b1 =
1)
b11111111 %
b11111111 +
b11111111 7
1$
#490000
0$
#495000
b10 =
b1 @
0)
1$
#500000
0$
#505000
1A
b0 <
b11111111 >
13
b10 @
1$
#510000
0$
#515000
b1 <
b11111110 >
1/
1.
1?
1$
#520000
0$
#525000
b1 B
b10101011 D
0.
0?
1$
#530000
0$
#535000
16
b10 <
b11111100 >
1.
11
1?
1$
#540000
0$
#545000
b10 B
b1010111 D
0.
0?
1$
#550000
0$
#555000
06
b11 <
b11111000 >
1.
01
1?
1$
#560000
0$
#565000
b11 B
b10101111 D
0.
0?
1$
#570000
0$
#575000
16
b100 <
b11110000 >
1.
11
1?
1$
#580000
0$
#585000
b100 B
b1011111 D
0.
0?
1$
#590000
0$
#595000
06
b101 <
b11100000 >
1.
01
1?
1$
#600000
0$
#605000
b101 B
b10111111 D
0.
0?
1$
#610000
0$
#615000
16
b110 <
b11000000 >
1.
11
1?
1$
#620000
0$
#625000
b110 B
b1111111 D
0.
0?
1$
#630000
0$
#635000
06
b111 <
b10000000 >
1.
01
1?
1$
#640000
0$
#645000
b111 B
b11111111 D
0.
0?
1$
#650000
0$
#655000
b11 =
16
b1000 <
b0 >
1.
11
1?
1$
#660000
0$
#665000
b0 =
b0 B
b11111111 -
b11111111 C
0.
b11 @
0?
1$
#670000
0$
#675000
0A
b0 @
12
03
b11111111 #
b11111111 4
1$
#680000
0$
#685000
06
b11111111 I
1!
01
0/
02
1$
#690000
0$
#695000
0!
b0 *
1$
#700000
0$
#705000
b0 %
b0 +
b0 7
b10000001 K
b10000001 &
1$
#710000
0$
#715000
b1 =
1)
b10000001 %
b10000001 +
b10000001 7
1$
#720000
0$
#725000
b10 =
b1 @
0)
1$
#730000
0$
#735000
1A
b10 @
b0 <
b10000001 >
13
1$
#740000
0$
#745000
16
11
b1 <
b10 >
1/
1.
1?
1$
#750000
0$
#755000
0.
b1 B
0?
1$
#760000
0$
#765000
b10 <
b100 >
0/
1.
1?
1$
#770000
0$
#775000
0.
b10 B
b11111110 D
0?
1$
#780000
0$
#785000
b11 <
b1000 >
1.
1?
1$
#790000
0$
#795000
0.
b11 B
b11111100 D
0?
1$
#800000
0$
#805000
b100 <
b10000 >
1.
1?
1$
#810000
0$
#815000
0.
b100 B
b11111000 D
0?
1$
#820000
0$
#825000
b101 <
b100000 >
1.
1?
1$
#830000
0$
#835000
0.
b101 B
b11110000 D
0?
1$
#840000
0$
#845000
b110 <
b1000000 >
1.
1?
1$
#850000
0$
#855000
0.
b110 B
b11100000 D
0?
1$
#860000
0$
#865000
b111 <
b10000000 >
1.
1?
1$
#870000
0$
#875000
0.
b111 B
b11000000 D
0?
1$
#880000
0$
#885000
b11 =
b1000 <
b0 >
1/
1.
1?
1$
#890000
0$
#895000
b0 =
b11 @
0.
b0 B
b10000001 -
b10000001 C
b10000001 D
0?
1$
#900000
0$
#905000
0A
b10000001 #
b10000001 4
12
03
b0 @
1$
#910000
0$
#915000
06
b10000001 I
0/
02
01
1!
1$
#920000
0$
#925000
0!
b11110000 "
b11110000 5
b0 #
b0 4
1(
b1 *
1$
#930000
0$
#935000
b0 %
b0 +
b0 7
1J
b1100011 K
b1100011 &
1$
#940000
0$
#945000
b1 =
1)
b1100011 %
b1100011 +
b1100011 7
1$
#950000
0$
#955000
b10 =
b1 @
0)
1$
#960000
0$
#965000
1E
b0 <
b1100011 >
13
b10 @
1$
#970000
0$
#975000
16
b1 <
b11000110 >
1.
10
1?
1$
#980000
0$
#985000
b1 F
b11100000 H
0.
0?
1$
#990000
0$
#995000
b10 <
b10001100 >
1/
1.
1?
1$
#1000000
0$
#1005000
b10 F
b11000001 H
0.
0?
1$
#1010000
0$
#1015000
b11 <
b11000 >
1.
1?
1$
#1020000
0$
#1025000
b11 F
b10000011 H
0.
0?
1$
#1030000
0$
#1035000
b100 <
b110000 >
0/
1.
1?
1$
#1040000
0$
#1045000
b100 F
b110 H
0.
0?
1$
#1050000
0$
#1055000
06
b101 <
b1100000 >
1.
00
1?
1$
#1060000
0$
#1065000
b101 F
b1100 H
0.
0?
1$
#1070000
0$
#1075000
b110 <
b11000000 >
1.
1?
1$
#1080000
0$
#1085000
b110 F
b11000 H
0.
0?
1$
#1090000
0$
#1095000
b111 <
b10000000 >
1/
1.
1?
1$
#1100000
0$
#1105000
b111 F
b110001 H
0.
0?
1$
#1110000
0$
#1115000
b11 =
b1000 <
b0 >
1.
1?
1$
#1120000
0$
#1125000
b0 =
b0 F
b1100011 ,
b1100011 G
b1100011 H
0.
b11 @
0?
1$
#1130000
0$
#1135000
0E
b0 @
12
03
b1100011 "
b1100011 5
1$
#1140000
0$
#1145000
b1100011 I
1!
0/
02
1$
#1150000
0$
#1155000
0!
b10 *
1$
#1160000
0$
#1165000
b0 %
b0 +
b0 7
b10001101 K
b10001101 &
1$
#1170000
0$
#1175000
b1 =
1)
b10001101 %
b10001101 +
b10001101 7
1$
#1180000
0$
#1185000
b10 =
b1 @
0)
1$
#1190000
0$
#1195000
1E
b10 @
b0 <
b10001101 >
13
1$
#1200000
0$
#1205000
b1 <
b11010 >
1/
1.
1?
1$
#1210000
0$
#1215000
0.
b1 F
b11000111 H
0?
1$
#1220000
0$
#1225000
16
10
b10 <
b110100 >
0/
1.
1?
1$
#1230000
0$
#1235000
0.
b10 F
b10001110 H
0?
1$
#1240000
0$
#1245000
b11 <
b1101000 >
1.
1?
1$
#1250000
0$
#1255000
0.
b11 F
b11100 H
0?
1$
#1260000
0$
#1265000
06
00
b100 <
b11010000 >
1.
1?
1$
#1270000
0$
#1275000
0.
b100 F
b111000 H
0?
1$
#1280000
0$
#1285000
b101 <
b10100000 >
1/
1.
1?
1$
#1290000
0$
#1295000
0.
b101 F
b1110001 H
0?
1$
#1300000
0$
#1305000
b110 <
b1000000 >
1.
1?
1$
#1310000
0$
#1315000
0.
b110 F
b11100011 H
0?
1$
#1320000
0$
#1325000
16
10
b111 <
b10000000 >
0/
1.
1?
1$
#1330000
0$
#1335000
0.
b111 F
b11000110 H
0?
1$
#1340000
0$
#1345000
b11 =
b1000 <
b0 >
1/
1.
1?
1$
#1350000
0$
#1355000
b0 =
b11 @
0.
b0 F
b10001101 ,
b10001101 G
b10001101 H
0?
1$
#1360000
0$
#1365000
0E
b10001101 "
b10001101 5
12
03
b0 @
1$
#1370000
0$
#1375000
06
b10001101 I
0/
02
00
1!
1$
#1380000
0$
#1385000
0!
b11 *
1$
#1390000
0$
#1395000
b0 %
b0 +
b0 7
b10010 K
b10010 &
1$
#1400000
0$
#1405000
b1 =
1)
b10010 %
b10010 +
b10010 7
1$
#1410000
0$
#1415000
b10 =
b1 @
0)
1$
#1420000
0$
#1425000
1E
b0 <
b10010 >
13
b10 @
1$
#1430000
0$
#1435000
16
b1 <
b100100 >
1.
10
1?
1$
#1440000
0$
#1445000
b1 F
b11010 H
0.
0?
1$
#1450000
0$
#1455000
06
b10 <
b1001000 >
1.
00
1?
1$
#1460000
0$
#1465000
b10 F
b110100 H
0.
0?
1$
#1470000
0$
#1475000
b11 <
b10010000 >
1.
1?
1$
#1480000
0$
#1485000
b11 F
b1101000 H
0.
0?
1$
#1490000
0$
#1495000
b100 <
b100000 >
1/
1.
1?
1$
#1500000
0$
#1505000
b100 F
b11010001 H
0.
0?
1$
#1510000
0$
#1515000
16
b101 <
b1000000 >
0/
1.
10
1?
1$
#1520000
0$
#1525000
b101 F
b10100010 H
0.
0?
1$
#1530000
0$
#1535000
b110 <
b10000000 >
1.
1?
1$
#1540000
0$
#1545000
b110 F
b1000100 H
0.
0?
1$
#1550000
0$
#1555000
06
b111 <
b0 >
1/
1.
00
1?
1$
#1560000
0$
#1565000
b111 F
b10001001 H
0.
0?
1$
#1570000
0$
#1575000
b11 =
16
b1000 <
0/
1.
10
1?
1$
#1580000
0$
#1585000
b0 =
b0 F
b10010 ,
b10010 G
b10010 H
0.
b11 @
0?
1$
#1590000
0$
#1595000
06
0E
b0 @
12
03
00
b10010 "
b10010 5
1$
#1600000
0$
#1605000
b10010 I
1!
02
1$
#1610000
0$
#1615000
0!
b100 *
1$
#1620000
0$
#1625000
b0 %
b0 +
b0 7
b1101 K
b1101 &
1$
#1630000
0$
#1635000
b1 =
1)
b1101 %
b1101 +
b1101 7
1$
#1640000
0$
#1645000
b10 =
b1 @
0)
1$
#1650000
0$
#1655000
1E
b10 @
b0 <
b1101 >
13
1$
#1660000
0$
#1665000
b1 <
b11010 >
1.
1?
1$
#1670000
0$
#1675000
0.
b1 F
b100100 H
0?
1$
#1680000
0$
#1685000
b10 <
b110100 >
1.
1?
1$
#1690000
0$
#1695000
0.
b10 F
b1001000 H
0?
1$
#1700000
0$
#1705000
b11 <
b1101000 >
1.
1?
1$
#1710000
0$
#1715000
0.
b11 F
b10010000 H
0?
1$
#1720000
0$
#1725000
16
10
b100 <
b11010000 >
1.
1?
1$
#1730000
0$
#1735000
0.
b100 F
b100000 H
0?
1$
#1740000
0$
#1745000
06
00
b101 <
b10100000 >
1/
1.
1?
1$
#1750000
0$
#1755000
0.
b101 F
b1000001 H
0?
1$
#1760000
0$
#1765000
b110 <
b1000000 >
1.
1?
1$
#1770000
0$
#1775000
0.
b110 F
b10000011 H
0?
1$
#1780000
0$
#1785000
16
10
b111 <
b10000000 >
0/
1.
1?
1$
#1790000
0$
#1795000
0.
b111 F
b110 H
0?
1$
#1800000
0$
#1805000
06
b11 =
00
b1000 <
b0 >
1/
1.
1?
1$
#1810000
0$
#1815000
b0 =
b11 @
0.
b0 F
b1101 ,
b1101 G
b1101 H
0?
1$
#1820000
0$
#1825000
0E
b1101 "
b1101 5
12
03
b0 @
1$
#1830000
0$
#1835000
b1101 I
0/
02
1!
1$
#1840000
0$
#1845000
0!
b0 "
b0 5
b10000001 #
b10000001 4
0(
b101 *
1$
#1850000
0$
#1855000
b0 %
b0 +
b0 7
0J
b111101 K
b111101 &
1$
#1860000
0$
#1865000
b1 =
1)
b111101 %
b111101 +
b111101 7
1$
#1870000
0$
#1875000
b10 =
b1 @
0)
1$
#1880000
0$
#1885000
1A
b0 <
b111101 >
13
b10 @
1$
#1890000
0$
#1895000
16
b1 <
b1111010 >
1.
11
1?
1$
#1900000
0$
#1905000
b1 B
b10 D
0.
0?
1$
#1910000
0$
#1915000
06
b10 <
b11110100 >
1.
01
1?
1$
#1920000
0$
#1925000
b10 B
b100 D
0.
0?
1$
#1930000
0$
#1935000
b11 <
b11101000 >
1/
1.
1?
1$
#1940000
0$
#1945000
b11 B
b1001 D
0.
0?
1$
#1950000
0$
#1955000
b100 <
b11010000 >
1.
1?
1$
#1960000
0$
#1965000
b100 B
b10011 D
0.
0?
1$
#1970000
0$
#1975000
b101 <
b10100000 >
1.
1?
1$
#1980000
0$
#1985000
b101 B
b100111 D
0.
0?
1$
#1990000
0$
#1995000
b110 <
b1000000 >
1.
1?
1$
#2000000
0$
#2005000
b110 B
b1001111 D
0.
0?
1$
#2010000
0$
#2015000
b111 <
b10000000 >
0/
1.
1?
1$
#2020000
0$
#2025000
b111 B
b10011110 D
0.
0?
1$
#2030000
0$
#2035000
b11 =
16
b1000 <
b0 >
1/
1.
11
1?
1$
#2040000
0$
#2045000
b0 =
b0 B
b111101 -
b111101 C
b111101 D
0.
b11 @
0?
1$
#2050000
0$
#2055000
06
0A
b0 @
12
03
01
b111101 #
b111101 4
1$
#2060000
0$
#2065000
b111101 I
1!
0/
02
1$
#2070000
0$
#2075000
0!
b1101 "
b1101 5
b0 #
b0 4
1(
b110 *
1$
#2080000
0$
#2085000
b0 %
b0 +
b0 7
1J
b10001100 K
b10001100 &
1$
#2090000
0$
#2095000
b1 =
1)
b10001100 %
b10001100 +
b10001100 7
1$
#2100000
0$
#2105000
b10 =
b1 @
0)
1$
#2110000
0$
#2115000
1E
b10 @
b0 <
b10001100 >
13
1$
#2120000
0$
#2125000
b1 <
b11000 >
1/
1.
1?
1$
#2130000
0$
#2135000
0.
b1 F
b11011 H
0?
1$
#2140000
0$
#2145000
b10 <
b110000 >
0/
1.
1?
1$
#2150000
0$
#2155000
0.
b10 F
b110110 H
0?
1$
#2160000
0$
#2165000
b11 <
b1100000 >
1.
1?
1$
#2170000
0$
#2175000
0.
b11 F
b1101100 H
0?
1$
#2180000
0$
#2185000
b100 <
b11000000 >
1.
1?
1$
#2190000
0$
#2195000
0.
b100 F
b11011000 H
0?
1$
#2200000
0$
#2205000
16
10
b101 <
b10000000 >
1/
1.
1?
1$
#2210000
0$
#2215000
0.
b101 F
b10110001 H
0?
1$
#2220000
0$
#2225000
b110 <
b0 >
1.
1?
1$
#2230000
0$
#2235000
0.
b110 F
b1100011 H
0?
1$
#2240000
0$
#2245000
06
00
b111 <
0/
1.
1?
1$
#2250000
0$
#2255000
0.
b111 F
b11000110 H
0?
1$
#2260000
0$
#2265000
16
b11 =
10
b1000 <
1.
1?
1$
#2270000
0$
#2275000
b0 =
b11 @
0.
b0 F
b10001100 ,
b10001100 G
b10001100 H
0?
1$
#2280000
0$
#2285000
0E
b10001100 "
b10001100 5
12
03
b0 @
1$
#2290000
0$
#2295000
06
b10001100 I
02
00
1!
1$
#2300000
0$
#2305000
0!
b111 *
1$
#2310000
0$
#2315000
b0 %
b0 +
b0 7
b11000110 K
b11000110 &
1$
#2320000
0$
#2325000
b1 =
1)
b11000110 %
b11000110 +
b11000110 7
1$
#2330000
0$
#2335000
b10 =
b1 @
0)
1$
#2340000
0$
#2345000
1E
b0 <
b11000110 >
13
b10 @
1$
#2350000
0$
#2355000
16
b1 <
b10001100 >
1/
1.
10
1?
1$
#2360000
0$
#2365000
b1 F
b11001 H
0.
0?
1$
#2370000
0$
#2375000
06
b10 <
b11000 >
1.
00
1?
1$
#2380000
0$
#2385000
b10 F
b110011 H
0.
0?
1$
#2390000
0$
#2395000
b11 <
b110000 >
0/
1.
1?
1$
#2400000
0$
#2405000
b11 F
b1100110 H
0.
0?
1$
#2410000
0$
#2415000
b100 <
b1100000 >
1.
1?
1$
#2420000
0$
#2425000
b100 F
b11001100 H
0.
0?
1$
#2430000
0$
#2435000
16
b101 <
b11000000 >
1.
10
1?
1$
#2440000
0$
#2445000
b101 F
b10011000 H
0.
0?
1$
#2450000
0$
#2455000
b110 <
b10000000 >
1/
1.
1?
1$
#2460000
0$
#2465000
b110 F
b110001 H
0.
0?
1$
#2470000
0$
#2475000
06
b111 <
b0 >
1.
00
1?
1$
#2480000
0$
#2485000
b111 F
b1100011 H
0.
0?
1$
#2490000
0$
#2495000
b11 =
b1000 <
0/
1.
1?
1$
#2500000
0$
#2505000
b0 =
b0 F
b11000110 ,
b11000110 G
b11000110 H
0.
b11 @
0?
1$
#2510000
0$
#2515000
16
0E
b0 @
12
03
10
b11000110 "
b11000110 5
1$
#2520000
0$
#2525000
06
b11000110 I
1!
00
02
1$
#2530000
0$
#2535000
0!
b1000 *
1$
#2540000
0$
#2545000
b0 %
b0 +
b0 7
b10101010 K
b10101010 &
1$
#2550000
0$
#2555000
b1 =
1)
b10101010 %
b10101010 +
b10101010 7
1$
#2560000
0$
#2565000
b10 =
b1 @
0)
1$
#2570000
0$
#2575000
1E
b10 @
b0 <
b10101010 >
13
1$
#2580000
0$
#2585000
16
10
b1 <
b1010100 >
1/
1.
1?
1$
#2590000
0$
#2595000
0.
b1 F
b10001101 H
0?
1$
#2600000
0$
#2605000
b10 <
b10101000 >
0/
1.
1?
1$
#2610000
0$
#2615000
0.
b10 F
b11010 H
0?
1$
#2620000
0$
#2625000
06
00
b11 <
b1010000 >
1/
1.
1?
1$
#2630000
0$
#2635000
0.
b11 F
b110101 H
0?
1$
#2640000
0$
#2645000
b100 <
b10100000 >
0/
1.
1?
1$
#2650000
0$
#2655000
0.
b100 F
b1101010 H
0?
1$
#2660000
0$
#2665000
b101 <
b1000000 >
1/
1.
1?
1$
#2670000
0$
#2675000
0.
b101 F
b11010101 H
0?
1$
#2680000
0$
#2685000
16
10
b110 <
b10000000 >
0/
1.
1?
1$
#2690000
0$
#2695000
0.
b110 F
b10101010 H
0?
1$
#2700000
0$
#2705000
b111 <
b0 >
1/
1.
1?
1$
#2710000
0$
#2715000
0.
b111 F
b1010101 H
0?
1$
#2720000
0$
#2725000
06
b11 =
00
b1000 <
0/
1.
1?
1$
#2730000
0$
#2735000
b0 =
b11 @
0.
b0 F
b10101010 ,
b10101010 G
b10101010 H
0?
1$
#2740000
0$
#2745000
16
0E
b10101010 "
b10101010 5
10
12
03
b0 @
1$
#2750000
0$
#2755000
06
b10101010 I
02
00
1!
1$
